depsland/__init__.py
depsland/__main__.py
depsland/api/__init__.py
depsland/api/dev_api/__init__.py
depsland/api/dev_api/build.py
depsland/api/dev_api/build_offline.py
depsland/api/dev_api/build_project.py
depsland/api/dev_api/build_project_template.json
depsland/api/dev_api/index.py
depsland/api/dev_api/init.py
depsland/api/dev_api/publish.py
depsland/api/self_api/__init__.py
depsland/api/self_api/upgrade.py
depsland/api/user_api/__init__.py
depsland/api/user_api/export.py
depsland/api/user_api/install.py
depsland/api/user_api/run.py
depsland/api/user_api/uninstall.py
depsland/assets/launcher.ico
depsland/assets/launcher.png
depsland/assets/python.ico
depsland/assets/python.png
depsland/assets/readme.md
depsland/chore/build.zip
depsland/chore/config.zip
depsland/chore/readme.md
depsland/chore/sidework.zip
depsland/config.py
depsland/depsolver/__init__.py
depsland/depsolver/poetry_lock_resolver.py
depsland/depsolver/requirements_lock.py
depsland/depsolver/resolver.py
depsland/depsolver/version_crawler.py
depsland/doctor.py
depsland/launcher.py
depsland/manifest/__init__.py
depsland/manifest/appinfo.py
depsland/manifest/manifest.py
depsland/normalization.py
depsland/oss/__init__.py
depsland/oss/_base.py
depsland/oss/aliyun_oss.py
depsland/oss/fake_oss.py
depsland/oss/get_oss.py
depsland/oss/local_oss.py
depsland/paths.py
depsland/platform/__init__.py
depsland/platform/launcher/__init__.py
depsland/platform/launcher/make_app/__init__.py
depsland/platform/launcher/make_app/make_app.py
depsland/platform/launcher/make_app/template/Contents/Info.plist
depsland/platform/launcher/make_app/template/Contents/MacOS/APP_NAME
depsland/platform/launcher/make_bat.py
depsland/platform/launcher/make_exe/__init__.py
depsland/platform/launcher/make_exe/bat_2_exe_1/__init__.py
depsland/platform/launcher/make_exe/bat_2_exe_1/main.py
depsland/platform/launcher/make_exe/bat_2_exe_1/rcedit.exe
depsland/platform/launcher/make_exe/bat_2_exe_1/template.exe
depsland-0.10.1.dist-info/entry_points.txt
depsland-0.10.1.dist-info/LICENSE
depsland-0.10.1.dist-info/METADATA
depsland-0.10.1.dist-info/WHEEL
depsland-0.10.1.dist-info/RECORD
